gsc/__init__.py
gsc/__main__.py
gsc/config.py
gsc/constants.py
gsc/core/__init__.py
gsc/core/base_model.py
gsc/core/rate_limit.py
gsc/core/request_decorator.py
gsc/core/rx_task.py
gsc/data/__init__.py
gsc/data/repository/__init__.py
gsc/data/repository/base_repository.py
gsc/data/repository/github_repository.py
gsc/data/repository/gitlab_repository.py
gsc/data/request/__init__.py
gsc/data/request/github_request.py
gsc/data/request/gitlab_request.py
gsc/data/response/__init__.py
gsc/data/response/github_response.py
gsc/data/response/gitlab_response.py
gsc/di/__init__.py
gsc/di/application_container.py
gsc/di/github_container.py
gsc/di/gitlab_container.py
gsc/domain/entities/__init__.py
gsc/domain/entities/github_model.py
gsc/domain/entities/gitlab_model.py
gsc/domain/use_cases/__init__.py
gsc/domain/use_cases/base_use_case.py
gsc/domain/use_cases/github_search_use_case.py
gsc/domain/use_cases/gitlab_search_use_case.py
gsc/presentation/__init__.py
gsc/presentation/command_line/__init__.py
gsc/presentation/command_line/cli.py
gsc/presentation/command_line/env_cli.py
gsc/presentation/command_line/github_cli.py
gsc/presentation/command_line/gitlab_cli.py
gsc/presentation/observer/__init__.py
gsc/presentation/observer/base_observer.py
gsc/presentation/observer/github_observer.py
gsc/presentation/observer/gitlab_observer.py
gsc/presentation/observer/plugin.py
gsc/utils.py
git_search_command-2.1.2.dist-info/LICENSE
git_search_command-2.1.2.dist-info/METADATA
git_search_command-2.1.2.dist-info/WHEEL
git_search_command-2.1.2.dist-info/entry_points.txt
git_search_command-2.1.2.dist-info/RECORD
