Metadata-Version: 2.1
Name: git-search-command
Version: 2.1.2
Summary: A simple tool to search the content in GitLab and GitHub.
Home-page: https://github.com/jamesnguyen46/git-search-command
License: Apache-2.0
Keywords: gitlab,search,command line,python,git,github
Author: jamesnguyen46
Author-email: thachnguyen1989@gmail.com
Maintainer: jamesnguyen46
Maintainer-email: thachnguyen1989@gmail.com
Requires-Python: >=3.7,<4
Classifier: Development Status :: 5 - Production/Stable
Classifier: Intended Audience :: Developers
Classifier: License :: OSI Approved :: Apache Software License
Classifier: Programming Language :: Python :: 3
Classifier: Programming Language :: Python :: 3.7
Classifier: Programming Language :: Python :: 3.8
Classifier: Programming Language :: Python :: 3.9
Classifier: Programming Language :: Python :: 3.10
Classifier: Programming Language :: Python :: 3.11
Classifier: Topic :: Internet :: WWW/HTTP :: Indexing/Search
Requires-Dist: click (>=8.0.3)
Requires-Dist: dependency-injector (>=4.0,<5.0)
Requires-Dist: jsonpickle (>=2.1.0)
Requires-Dist: python-dotenv (>=0.19.2)
Requires-Dist: requests (>=2.26.0)
Requires-Dist: rx (>=3.2.0)
Requires-Dist: tabulate (>=0.9.0,<0.10.0)
Project-URL: Bug Reports, https://github.com/jamesnguyen46/git-search-command/issues
Project-URL: Documentation, https://github.com/jamesnguyen46/git-search-command/wiki
Project-URL: Repository, https://github.com/jamesnguyen46/git-search-command
